{
  "Events": [
    {
      "status": "ACTIVE",
      "headline": "Caltrans : Long-term construction on CA-29 Southbound ramp to I-80 W (Vallejo). Connector ramp closed. Expect delays. From 5:30 AM Monday, February 28, 2022 to 12:00 AM Friday, June 30, 2023.",
      "event_type": "CONSTRUCTION",
      "event_subtypes": {
        "event_subtype": "Long-term construction"
      },
      "severity": "Unknown",
      "created": "2022-02-28T13:29Z",
      "updated": "2022-05-10T12:10Z",
      "areas": {
        "area": {
          "name": "Solano",
          "id": "5396987",
          "link": {
            "@rel": "self",
            "@href": "http://geonames.org/5396987/"
          }
        }
      },
      "geography": {
        "crs": {
          "type": "name",
          "properties": {
            "name": "urn:ogc:def:crs:EPSG::4326"
          }
        },
        "type": "Point",
        "coordinates": [
          -122.230545,
          38.074249
        ]
      },
      "source_type": {
        "@xmlns": "http://511.org/open511-extensions",
        "#text": "Caltrans"
      },
      "roads": [
        {
          "name": "CA-29 S",
          "from": "I-80 W",
          "direction": "Southbound",
          "state": "SOME_LANES_CLOSED",
          "lane_type": {
            "@xmlns": "http://511.org/open511-extensions",
            "#text": "Connector ramp"
          },
          "lane_status": {
            "@xmlns": "http://511.org/open511-extensions",
            "#text": "closed"
          },
          "road_advisory": {
            "@xmlns": "http://511.org/open511-extensions",
            "#text": "Expect delays"
          },
          "article": {
            "@xmlns": "http://511.org/open511-extensions",
            "#text": "ramp to"
          }
        }
      ],
      "schedule": {
        "intervals": [
          "2022-02-28T13:30Z/2023-06-30T07:00Z"
        ]
      },
      "extension": {
        "message-header": {
          "event-message-time-stamp": "2022-05-10T16:49:07.13136"
        },
        "event-reference": {
          "event-identifier": "876732"
        },
        "event-status": "new",
        "details": {
          "eventElementDetails": {
            "event-element-sequence": "1",
            "event-element-description": {
              "eventDescription": [
                {
                  "event-phrase": {
                    "eventType": {
                      "incident": "Long-term construction"
                    }
                  }
                },
                {
                  "event-advice": "(unknown)"
                },
                {
                  "event-additional-text": {
                    "eventAdditionalText": {
                      "event-description": "Caltrans : Long-term construction on CA-29 Southbound ramp to I-80 W (Vallejo). Connector ramp closed. Expect delays. From 5:30 AM Monday, February 28, 2022 to 12:00 AM Friday, June 30, 2023."
                    }
                  }
                }
              ]
            },
            "event-element-location": {
              "event-location-type": {
                "event-location-type-link": {
                  "event-location-type-area": "CA095",
                  "link-road-designator": "CA-29 S",
                  "link-from-road": "I-80 W",
                  "link-to-road": null,
                  "link-from-city": "Vallejo",
                  "link-to-city": null,
                  "link-primary-location": {
                    "event-location-coordinates-latitude": "38.074249",
                    "event-location-coordinates-longitude": "-122.230545"
                  }
                }
              }
            },
            "event-element-times": {
              "update-time": "2022-05-10T05:10:15.44340",
              "valid-period": {
                "event-timeline-estimated-duration": "0"
              },
              "start-time": "2022-02-28T05:30:00.00000",
              "cleared-time": "2023-06-30T00:00:00.00000",
              "utc-offset": "-0700"
            },
            "event-element-source": {
              "event-organization-reported-identifier": "1004"
            }
          }
        },
        "EventImpact": "Unknown",
        "RoadClosed": "false",
        "ivr-eventStatus": "2",
        "ivr-eventClass": "4",
        "ivr-eventDirection": "Southbound",
        "ivr-lastUpdateDttm": "2022-05-10T05:10:15.44340",
        "ivr-article": "ramp to",
        "ivr-county": "Solano",
        "ivr-laneStatus": "closed",
        "ivr-totalLanes": "Connector ramp",
        "ivr-genOtherText": "Expect delays",
        "EventSourceName": "Caltrans",
        "ivr-completeFlag": "1"
      }
    },
    {
      "status": "ACTIVE",
      "headline": "CHP : High winds on I-580 Eastbound and Westbound between S Vasco Rd (Livermore) and Grant Line Rd (Unincorporated). Lanes affected. Traffic advisory in effect.",
      "event_type": "INCIDENT",
      "event_subtypes": {
        "event_subtype": "High winds"
      },
      "severity": "Moderate",
      "created": "2022-05-09T12:13Z",
      "updated": "2022-05-10T23:00Z",
      "areas": {
        "area": {
          "name": "Alameda",
          "id": "5322745",
          "link": {
            "@rel": "self",
            "@href": "http://geonames.org/5322745/"
          }
        }
      },
      "geography": {
        "crs": {
          "type": "name",
          "properties": {
            "name": "urn:ogc:def:crs:EPSG::4326"
          }
        },
        "type": "Point",
        "coordinates": [
          -121.723709,
          37.709
        ]
      },
      "source_type": {
        "@xmlns": "http://511.org/open511-extensions",
        "#text": "CHP"
      },
      "roads": [
        {
          "name": "I-580 E",
          "from": "S Vasco Rd",
          "to": "Grant Line Rd",
          "direction": "Eastbound and Westbound",
          "state": "SOME_LANES_CLOSED",
          "lane_type": {
            "@xmlns": "http://511.org/open511-extensions",
            "#text": "Lanes"
          },
          "lane_status": {
            "@xmlns": "http://511.org/open511-extensions",
            "#text": "affected"
          },
          "road_advisory": {
            "@xmlns": "http://511.org/open511-extensions",
            "#text": "Traffic advisory in effect"
          },
          "article": {
            "@xmlns": "http://511.org/open511-extensions",
            "#text": "between"
          }
        }
      ],
      "schedule": {
        "intervals": [
          "2022-05-09T12:13Z/"
        ]
      },
      "extension": {
        "message-header": {
          "event-message-time-stamp": "2022-05-10T16:49:07.13136"
        },
        "event-reference": {
          "event-identifier": "901759"
        },
        "event-status": "new",
        "details": {
          "eventElementDetails": {
            "event-element-sequence": "1",
            "event-element-description": {
              "eventDescription": [
                {
                  "event-phrase": {
                    "eventType": {
                      "incident": "High winds"
                    }
                  }
                },
                {
                  "event-advice": "(unknown)"
                },
                {
                  "event-additional-text": {
                    "eventAdditionalText": {
                      "event-description": "CHP : High winds on I-580 Eastbound and Westbound between S Vasco Rd (Livermore) and Grant Line Rd (Unincorporated). Lanes affected. Traffic advisory in effect."
                    }
                  }
                }
              ]
            },
            "event-element-location": {
              "event-location-type": {
                "event-location-type-link": {
                  "event-location-type-area": "CA001",
                  "link-road-designator": "I-580 E",
                  "link-from-road": "S Vasco Rd",
                  "link-to-road": "Grant Line Rd",
                  "link-from-city": "Livermore",
                  "link-to-city": "Unincorporated",
                  "link-primary-location": {
                    "event-location-coordinates-latitude": "37.709",
                    "event-location-coordinates-longitude": "-121.723709"
                  }
                }
              }
            },
            "event-element-times": {
              "update-time": "2022-05-10T16:00:37.75870",
              "valid-period": {
                "event-timeline-estimated-duration": "37"
              },
              "start-time": "2022-05-09T05:13:00.00000",
              "cleared-time": null,
              "utc-offset": "-0700"
            },
            "event-element-source": {
              "event-organization-reported-identifier": "1003"
            }
          }
        },
        "EventImpact": "Moderate",
        "RoadClosed": "false",
        "ivr-eventStatus": "2",
        "ivr-eventClass": "2",
        "ivr-eventDirection": "Eastbound and Westbound",
        "ivr-lastUpdateDttm": "2022-05-10T16:00:37.75870",
        "ivr-article": "between",
        "ivr-county": "Alameda",
        "ivr-laneStatus": "affected",
        "ivr-totalLanes": "Lanes",
        "ivr-impact": "Always play incident",
        "ivr-genOtherText": "Traffic advisory in effect",
        "EventSourceName": "CHP",
        "ivr-completeFlag": "1"
      }
    },
    {
      "status": "ACTIVE",
      "headline": "Caltrans : Roadwork on CA-13 Southbound at Telegraph Ave (Berkeley). Right lane and shoulder closed until 8 PM. From 7:00 AM Tuesday, May 10, 2022 to 8:00 PM Tuesday, May 10, 2022.",
      "event_type": "CONSTRUCTION",
      "event_subtypes": {
        "event_subtype": "Roadwork"
      },
      "severity": "Unknown",
      "created": "2022-05-10T14:51Z",
      "updated": "2022-05-10T23:47Z",
      "areas": {
        "area": {
          "name": "Alameda",
          "id": "5322745",
          "link": {
            "@rel": "self",
            "@href": "http://geonames.org/5322745/"
          }
        }
      },
      "geography": {
        "crs": {
          "type": "name",
          "properties": {
            "name": "urn:ogc:def:crs:EPSG::4326"
          }
        },
        "type": "Point",
        "coordinates": [
          -122.261315,
          37.855943
        ]
      },
      "source_type": {
        "@xmlns": "http://511.org/open511-extensions",
        "#text": "Caltrans"
      },
      "source_id": {
        "@xmlns": "http://511.org/open511-extensions",
        "#text": "P13CA-0001-2022-05-10-07:01:00"
      },
      "roads": [
        {
          "name": "CA-13 S",
          "from": "Telegraph Ave",
          "direction": "Southbound",
          "state": "SOME_LANES_CLOSED",
          "lane_type": {
            "@xmlns": "http://511.org/open511-extensions",
            "#text": "Right lane and shoulder"
          },
          "lane_status": {
            "@xmlns": "http://511.org/open511-extensions",
            "#text": "closed"
          },
          "road_advisory": {
            "@xmlns": "http://511.org/open511-extensions",
            "#text": "until 8 PM"
          },
          "article": {
            "@xmlns": "http://511.org/open511-extensions",
            "#text": "at"
          }
        }
      ],
      "schedule": {
        "intervals": [
          "2022-05-10T14:01Z/2022-05-11T03:01Z"
        ]
      },
      "extension": {
        "message-header": {
          "event-message-time-stamp": "2022-05-10T16:49:07.13136"
        },
        "event-reference": {
          "event-identifier": "902188"
        },
        "event-status": "new",
        "details": {
          "eventElementDetails": {
            "event-element-sequence": "2",
            "event-element-description": {
              "eventDescription": [
                {
                  "event-phrase": {
                    "eventType": {
                      "incident": "Roadwork"
                    }
                  }
                },
                {
                  "event-advice": "(unknown)"
                },
                {
                  "event-additional-text": {
                    "eventAdditionalText": {
                      "event-description": "Caltrans : Roadwork on CA-13 Southbound at Telegraph Ave (Berkeley). Right lane and shoulder closed until 8 PM. From 7:00 AM Tuesday, May 10, 2022 to 8:00 PM Tuesday, May 10, 2022."
                    }
                  }
                }
              ]
            },
            "event-element-location": {
              "event-location-type": {
                "event-location-type-link": {
                  "event-location-type-area": "CA001",
                  "link-road-designator": "CA-13 S",
                  "link-from-road": "Telegraph Ave",
                  "link-to-road": null,
                  "link-from-city": "Berkeley",
                  "link-to-city": null,
                  "link-primary-location": {
                    "event-location-coordinates-latitude": "37.855943",
                    "event-location-coordinates-longitude": "-122.261315"
                  }
                }
              }
            },
            "event-element-times": {
              "update-time": "2022-05-10T16:47:47.39670",
              "valid-period": {
                "event-timeline-estimated-duration": "0"
              },
              "start-time": "2022-05-10T07:01:00.00000",
              "cleared-time": "2022-05-10T20:01:00.00000",
              "utc-offset": "-0700"
            },
            "event-element-source": {
              "event-organization-reported-identifier": "1004"
            }
          }
        },
        "EventImpact": "Unknown",
        "RoadClosed": "false",
        "ivr-eventStatus": "2",
        "ivr-eventClass": "4",
        "ivr-eventDirection": "Southbound",
        "ivr-lastUpdateDttm": "2022-05-10T16:47:47.39670",
        "ivr-article": "at",
        "ivr-county": "Alameda",
        "ivr-laneStatus": "closed",
        "ivr-totalLanes": "Right lane and shoulder",
        "ivr-genOtherText": "until 8 PM",
        "SourceEventID": "P13CA-0001-2022-05-10-07:01:00",
        "EventSourceName": "Caltrans",
        "ivr-completeFlag": "1"
      }
    },
    {
      "status": "ACTIVE",
      "headline": "Caltrans : Roadwork on CA-82 Northbound between Peninsula Ave (Burlingame) and Broadway (Burlingame). Lane closed until 5 PM. From 7:00 AM Tuesday, May 10, 2022 to 5:00 PM Tuesday, May 10, 2022.",
      "event_type": "CONSTRUCTION",
      "event_subtypes": {
        "event_subtype": "Roadwork"
      },
      "severity": "Unknown",
      "created": "2022-05-10T15:04Z",
      "updated": "2022-05-10T23:47Z",
      "areas": {
        "area": {
          "name": "San Mateo",
          "id": "5392427",
          "link": {
            "@rel": "self",
            "@href": "http://geonames.org/5392427/"
          }
        }
      },
      "geography": {
        "crs": {
          "type": "name",
          "properties": {
            "name": "urn:ogc:def:crs:EPSG::4326"
          }
        },
        "type": "Point",
        "coordinates": [
          -122.342939,
          37.57452
        ]
      },
      "source_type": {
        "@xmlns": "http://511.org/open511-extensions",
        "#text": "Caltrans"
      },
      "source_id": {
        "@xmlns": "http://511.org/open511-extensions",
        "#text": "P82JB-0007-2022-05-10-07:01:00"
      },
      "roads": [
        {
          "name": "CA-82 N",
          "from": "Peninsula Ave",
          "to": "Broadway",
          "direction": "Northbound",
          "state": "SOME_LANES_CLOSED",
          "lane_type": {
            "@xmlns": "http://511.org/open511-extensions",
            "#text": "Lane"
          },
          "lane_status": {
            "@xmlns": "http://511.org/open511-extensions",
            "#text": "closed"
          },
          "road_advisory": {
            "@xmlns": "http://511.org/open511-extensions",
            "#text": "until 5 PM"
          },
          "article": {
            "@xmlns": "http://511.org/open511-extensions",
            "#text": "between"
          }
        }
      ],
      "schedule": {
        "intervals": [
          "2022-05-10T14:01Z/2022-05-11T00:01Z"
        ]
      },
      "extension": {
        "message-header": {
          "event-message-time-stamp": "2022-05-10T16:49:07.13136"
        },
        "event-reference": {
          "event-identifier": "902192"
        },
        "event-status": "new",
        "details": {
          "eventElementDetails": {
            "event-element-sequence": "2",
            "event-element-description": {
              "eventDescription": [
                {
                  "event-phrase": {
                    "eventType": {
                      "incident": "Roadwork"
                    }
                  }
                },
                {
                  "event-advice": "(unknown)"
                },
                {
                  "event-additional-text": {
                    "eventAdditionalText": {
                      "event-description": "Caltrans : Roadwork on CA-82 Northbound between Peninsula Ave (Burlingame) and Broadway (Burlingame). Lane closed until 5 PM. From 7:00 AM Tuesday, May 10, 2022 to 5:00 PM Tuesday, May 10, 2022."
                    }
                  }
                }
              ]
            },
            "event-element-location": {
              "event-location-type": {
                "event-location-type-link": {
                  "event-location-type-area": "CA081",
                  "link-road-designator": "CA-82 N",
                  "link-from-road": "Peninsula Ave",
                  "link-to-road": "Broadway",
                  "link-from-city": "Burlingame",
                  "link-to-city": "Burlingame",
                  "link-primary-location": {
                    "event-location-coordinates-latitude": "37.57452",
                    "event-location-coordinates-longitude": "-122.342939"
                  }
                }
              }
            },
            "event-element-times": {
              "update-time": "2022-05-10T16:47:47.72380",
              "valid-period": {
                "event-timeline-estimated-duration": "0"
              },
              "start-time": "2022-05-10T07:01:00.00000",
              "cleared-time": "2022-05-10T17:01:00.00000",
              "utc-offset": "-0700"
            },
            "event-element-source": {
              "event-organization-reported-identifier": "1004"
            }
          }
        },
        "EventImpact": "Unknown",
        "RoadClosed": "false",
        "ivr-eventStatus": "2",
        "ivr-eventClass": "4",
        "ivr-eventDirection": "Northbound",
        "ivr-lastUpdateDttm": "2022-05-10T16:47:47.72380",
        "ivr-article": "between",
        "ivr-county": "San Mateo",
        "ivr-laneStatus": "closed",
        "ivr-totalLanes": "Lane",
        "ivr-genOtherText": "until 5 PM",
        "SourceEventID": "P82JB-0007-2022-05-10-07:01:00",
        "EventSourceName": "Caltrans",
        "ivr-completeFlag": "1"
      }
    },
    {
      "status": "ACTIVE",
      "headline": "Caltrans : Roadwork on CA-82 Southbound between Broadway (Burlingame) and Peninsula Ave (Burlingame). Lane closed until 5 PM. From 7:00 AM Tuesday, May 10, 2022 to 5:00 PM Tuesday, May 10, 2022.",
      "event_type": "CONSTRUCTION",
      "event_subtypes": {
        "event_subtype": "Roadwork"
      },
      "severity": "Unknown",
      "created": "2022-05-10T15:04Z",
      "updated": "2022-05-10T23:47Z",
      "areas": {
        "area": {
          "name": "San Mateo",
          "id": "5392427",
          "link": {
            "@rel": "self",
            "@href": "http://geonames.org/5392427/"
          }
        }
      },
      "geography": {
        "crs": {
          "type": "name",
          "properties": {
            "name": "urn:ogc:def:crs:EPSG::4326"
          }
        },
        "type": "Point",
        "coordinates": [
          -122.361749,
          37.581664
        ]
      },
      "source_type": {
        "@xmlns": "http://511.org/open511-extensions",
        "#text": "Caltrans"
      },
      "source_id": {
        "@xmlns": "http://511.org/open511-extensions",
        "#text": "P82JB-0012-2022-05-10-07:01:00"
      },
      "roads": [
        {
          "name": "CA-82 S",
          "from": "Broadway",
          "to": "Peninsula Ave",
          "direction": "Southbound",
          "state": "SOME_LANES_CLOSED",
          "lane_type": {
            "@xmlns": "http://511.org/open511-extensions",
            "#text": "Lane"
          },
          "lane_status": {
            "@xmlns": "http://511.org/open511-extensions",
            "#text": "closed"
          },
          "road_advisory": {
            "@xmlns": "http://511.org/open511-extensions",
            "#text": "until 5 PM"
          },
          "article": {
            "@xmlns": "http://511.org/open511-extensions",
            "#text": "between"
          }
        }
      ],
      "schedule": {
        "intervals": [
          "2022-05-10T14:01Z/2022-05-11T00:01Z"
        ]
      },
      "extension": {
        "message-header": {
          "event-message-time-stamp": "2022-05-10T16:49:07.13136"
        },
        "event-reference": {
          "event-identifier": "902193"
        },
        "event-status": "new",
        "details": {
          "eventElementDetails": {
            "event-element-sequence": "2",
            "event-element-description": {
              "eventDescription": [
                {
                  "event-phrase": {
                    "eventType": {
                      "incident": "Roadwork"
                    }
                  }
                },
                {
                  "event-advice": "(unknown)"
                },
                {
                  "event-additional-text": {
                    "eventAdditionalText": {
                      "event-description": "Caltrans : Roadwork on CA-82 Southbound between Broadway (Burlingame) and Peninsula Ave (Burlingame). Lane closed until 5 PM. From 7:00 AM Tuesday, May 10, 2022 to 5:00 PM Tuesday, May 10, 2022."
                    }
                  }
                }
              ]
            },
            "event-element-location": {
              "event-location-type": {
                "event-location-type-link": {
                  "event-location-type-area": "CA081",
                  "link-road-designator": "CA-82 S",
                  "link-from-road": "Broadway",
                  "link-to-road": "Peninsula Ave",
                  "link-from-city": "Burlingame",
                  "link-to-city": "Burlingame",
                  "link-primary-location": {
                    "event-location-coordinates-latitude": "37.581664",
                    "event-location-coordinates-longitude": "-122.361749"
                  }
                }
              }
            },
            "event-element-times": {
              "update-time": "2022-05-10T16:47:48.06010",
              "valid-period": {
                "event-timeline-estimated-duration": "0"
              },
              "start-time": "2022-05-10T07:01:00.00000",
              "cleared-time": "2022-05-10T17:01:00.00000",
              "utc-offset": "-0700"
            },
            "event-element-source": {
              "event-organization-reported-identifier": "1004"
            }
          }
        },
        "EventImpact": "Unknown",
        "RoadClosed": "false",
        "ivr-eventStatus": "2",
        "ivr-eventClass": "4",
        "ivr-eventDirection": "Southbound",
        "ivr-lastUpdateDttm": "2022-05-10T16:47:48.06010",
        "ivr-article": "between",
        "ivr-county": "San Mateo",
        "ivr-laneStatus": "closed",
        "ivr-totalLanes": "Lane",
        "ivr-genOtherText": "until 5 PM",
        "SourceEventID": "P82JB-0012-2022-05-10-07:01:00",
        "EventSourceName": "Caltrans",
        "ivr-completeFlag": "1"
      }
    },
    {
      "status": "ACTIVE",
      "headline": "CHP : High winds on I-80 Eastbound and Westbound between Fremont St (San Francisco) and Bay Bridge - Toll Plaza (Oakland). Lanes affected. Traffic advisory in effect.",
      "event_type": "INCIDENT",
      "event_subtypes": {
        "event_subtype": "High winds"
      },
      "severity": "Minor",
      "created": "2022-05-10T20:25Z",
      "updated": "2022-05-10T23:00Z",
      "areas": {
        "area": {
          "name": "San Francisco",
          "id": "5391997",
          "link": {
            "@rel": "self",
            "@href": "http://geonames.org/5391997/"
          }
        }
      },
      "geography": {
        "crs": {
          "type": "name",
          "properties": {
            "name": "urn:ogc:def:crs:EPSG::4326"
          }
        },
        "type": "Point",
        "coordinates": [
          -122.390923,
          37.786093
        ]
      },
      "source_type": {
        "@xmlns": "http://511.org/open511-extensions",
        "#text": "CHP"
      },
      "source_id": {
        "@xmlns": "http://511.org/open511-extensions",
        "#text": "220510GG01127"
      },
      "roads": [
        {
          "name": "I-80 W",
          "from": "Fremont St",
          "to": "Bay Bridge - Toll Plaza",
          "direction": "Eastbound and Westbound",
          "state": "SOME_LANES_CLOSED",
          "lane_type": {
            "@xmlns": "http://511.org/open511-extensions",
            "#text": "Lanes"
          },
          "lane_status": {
            "@xmlns": "http://511.org/open511-extensions",
            "#text": "affected"
          },
          "road_advisory": {
            "@xmlns": "http://511.org/open511-extensions",
            "#text": "Traffic advisory in effect"
          },
          "article": {
            "@xmlns": "http://511.org/open511-extensions",
            "#text": "between"
          }
        }
      ],
      "schedule": {
        "intervals": [
          "2022-05-10T20:25Z/"
        ]
      },
      "extension": {
        "message-header": {
          "event-message-time-stamp": "2022-05-10T16:49:07.13136"
        },
        "event-reference": {
          "event-identifier": "902301"
        },
        "event-status": "new",
        "details": {
          "eventElementDetails": {
            "event-element-sequence": "4",
            "event-element-description": {
              "eventDescription": [
                {
                  "event-phrase": {
                    "eventType": {
                      "incident": "High winds"
                    }
                  }
                },
                {
                  "event-advice": "(unknown)"
                },
                {
                  "event-additional-text": {
                    "eventAdditionalText": {
                      "event-description": "CHP : High winds on I-80 Eastbound and Westbound between Fremont St (San Francisco) and Bay Bridge - Toll Plaza (Oakland). Lanes affected. Traffic advisory in effect."
                    }
                  }
                }
              ]
            },
            "event-element-location": {
              "event-location-type": {
                "event-location-type-link": {
                  "event-location-type-area": "CA075",
                  "link-road-designator": "I-80 W",
                  "link-from-road": "Fremont St",
                  "link-to-road": "Bay Bridge - Toll Plaza",
                  "link-from-city": "San Francisco",
                  "link-to-city": "Oakland",
                  "link-primary-location": {
                    "event-location-coordinates-latitude": "37.786093",
                    "event-location-coordinates-longitude": "-122.390923"
                  }
                }
              }
            },
            "event-element-times": {
              "update-time": "2022-05-10T16:00:37.62420",
              "valid-period": {
                "event-timeline-estimated-duration": "7"
              },
              "start-time": "2022-05-10T13:25:00.00000",
              "cleared-time": null,
              "utc-offset": "-0700"
            },
            "event-element-source": {
              "event-organization-reported-identifier": "1003"
            }
          }
        },
        "EventImpact": "Minor",
        "RoadClosed": "false",
        "ivr-eventStatus": "2",
        "ivr-eventClass": "1",
        "ivr-eventDirection": "Eastbound and Westbound",
        "ivr-lastUpdateDttm": "2022-05-10T16:00:37.62420",
        "ivr-article": "between",
        "ivr-county": "San Francisco",
        "ivr-laneStatus": "affected",
        "ivr-totalLanes": "Lanes",
        "ivr-impact": "Always play incident",
        "ivr-genOtherText": "Traffic advisory in effect",
        "SourceEventID": "220510GG01127",
        "EventSourceName": "CHP",
        "ivr-completeFlag": "1"
      }
    },
    {
      "status": "ACTIVE",
      "headline": "CHP : Severe traffic alert and Overturned tractor trailer and Traffic Collision on CA-87 Northbound north of W Capitol Expy (San Jose). Right and center lanes blocked. Expect delays.",
      "event_type": "INCIDENT",
      "event_subtypes": {
        "event_subtype": [
          "Traffic Collision",
          "Overturned tractor trailer",
          "Severe traffic alert"
        ]
      },
      "severity": "Severe",
      "created": "2022-05-10T22:53Z",
      "updated": "2022-05-10T23:40Z",
      "areas": {
        "area": {
          "name": "Santa Clara",
          "id": "5393021",
          "link": {
            "@rel": "self",
            "@href": "http://geonames.org/5393021/"
          }
        }
      },
      "geography": {
        "crs": {
          "type": "name",
          "properties": {
            "name": "urn:ogc:def:crs:EPSG::4326"
          }
        },
        "type": "Point",
        "coordinates": [
          -121.865022,
          37.280366
        ]
      },
      "source_type": {
        "@xmlns": "http://511.org/open511-extensions",
        "#text": "CHP"
      },
      "source_id": {
        "@xmlns": "http://511.org/open511-extensions",
        "#text": "220510GG01476"
      },
      "roads": [
        {
          "name": "CA-87 N",
          "from": "W Capitol Expy",
          "direction": "Northbound",
          "state": "SOME_LANES_CLOSED",
          "lane_type": {
            "@xmlns": "http://511.org/open511-extensions",
            "#text": "Right and center lanes"
          },
          "lane_status": {
            "@xmlns": "http://511.org/open511-extensions",
            "#text": "blocked"
          },
          "road_advisory": {
            "@xmlns": "http://511.org/open511-extensions",
            "#text": "Expect delays"
          },
          "article": {
            "@xmlns": "http://511.org/open511-extensions",
            "#text": "north of"
          }
        }
      ],
      "schedule": {
        "intervals": [
          "2022-05-10T23:34Z/"
        ]
      },
      "extension": {
        "message-header": {
          "event-message-time-stamp": "2022-05-10T16:49:07.13136"
        },
        "event-reference": {
          "event-identifier": "902361"
        },
        "event-status": "new",
        "details": {
          "eventElementDetails": {
            "event-element-sequence": "4",
            "event-element-description": {
              "eventDescription": [
                {
                  "event-phrase": {
                    "eventType": [
                      {
                        "incident": "Traffic Collision"
                      },
                      {
                        "incident": "Overturned tractor trailer"
                      },
                      {
                        "incident": "Severe traffic alert"
                      }
                    ]
                  }
                },
                {
                  "event-advice": "(unknown)"
                },
                {
                  "event-additional-text": {
                    "eventAdditionalText": {
                      "event-description": "CHP : Severe traffic alert and Overturned tractor trailer and Traffic Collision on CA-87 Northbound north of W Capitol Expy (San Jose). Right and center lanes blocked. Expect delays."
                    }
                  }
                }
              ]
            },
            "event-element-location": {
              "event-location-type": {
                "event-location-type-link": {
                  "event-location-type-area": "CA085",
                  "link-road-designator": "CA-87 N",
                  "link-from-road": "W Capitol Expy",
                  "link-to-road": null,
                  "link-from-city": "San Jose",
                  "link-to-city": null,
                  "link-primary-location": {
                    "event-location-coordinates-latitude": "37.280366",
                    "event-location-coordinates-longitude": "-121.865022"
                  }
                }
              }
            },
            "event-element-times": {
              "update-time": "2022-05-10T16:40:34.98470",
              "valid-period": {
                "event-timeline-estimated-duration": "74.5"
              },
              "start-time": "2022-05-10T16:34:00.00000",
              "cleared-time": null,
              "utc-offset": "-0700"
            },
            "event-element-source": {
              "event-organization-reported-identifier": "1003"
            }
          }
        },
        "EventImpact": "Severe",
        "RoadClosed": "false",
        "ivr-eventStatus": "2",
        "ivr-eventClass": "5",
        "ivr-eventDirection": "Northbound",
        "ivr-lastUpdateDttm": "2022-05-10T16:40:34.98470",
        "ivr-article": "north of",
        "ivr-county": "Santa Clara",
        "ivr-laneStatus": "blocked",
        "ivr-totalLanes": "Right and center lanes",
        "ivr-impact": "Always play incident",
        "ivr-genOtherText": "Expect delays",
        "SourceEventID": "220510GG01476",
        "EventSourceName": "CHP",
        "ivr-completeFlag": "1"
      }
    },
    {
      "status": "ACTIVE",
      "headline": "CHP : Traffic Collision on I-580 Eastbound ramp to CA-24 E (Oakland). Left lane blocked. Expect delays.",
      "event_type": "INCIDENT",
      "event_subtypes": {
        "event_subtype": "Traffic Collision"
      },
      "severity": "Moderate",
      "created": "2022-05-10T23:06Z",
      "updated": "2022-05-10T23:41Z",
      "areas": {
        "area": {
          "name": "Alameda",
          "id": "5322745",
          "link": {
            "@rel": "self",
            "@href": "http://geonames.org/5322745/"
          }
        }
      },
      "geography": {
        "crs": {
          "type": "name",
          "properties": {
            "name": "urn:ogc:def:crs:EPSG::4326"
          }
        },
        "type": "Point",
        "coordinates": [
          -122.274818,
          37.825706
        ]
      },
      "source_type": {
        "@xmlns": "http://511.org/open511-extensions",
        "#text": "CHP"
      },
      "source_id": {
        "@xmlns": "http://511.org/open511-extensions",
        "#text": "220510GG01523"
      },
      "roads": [
        {
          "name": "I-580 E",
          "from": "CA-24 E",
          "direction": "Eastbound",
          "state": "SOME_LANES_CLOSED",
          "lane_type": {
            "@xmlns": "http://511.org/open511-extensions",
            "#text": "Left lane"
          },
          "lane_status": {
            "@xmlns": "http://511.org/open511-extensions",
            "#text": "blocked"
          },
          "road_advisory": {
            "@xmlns": "http://511.org/open511-extensions",
            "#text": "Expect delays"
          },
          "article": {
            "@xmlns": "http://511.org/open511-extensions",
            "#text": "ramp to"
          }
        }
      ],
      "schedule": {
        "intervals": [
          "2022-05-10T23:39Z/"
        ]
      },
      "extension": {
        "message-header": {
          "event-message-time-stamp": "2022-05-10T16:49:07.13136"
        },
        "event-reference": {
          "event-identifier": "902370"
        },
        "event-status": "new",
        "details": {
          "eventElementDetails": {
            "event-element-sequence": "4",
            "event-element-description": {
              "eventDescription": [
                {
                  "event-phrase": {
                    "eventType": {
                      "incident": "Traffic Collision"
                    }
                  }
                },
                {
                  "event-advice": "(unknown)"
                },
                {
                  "event-additional-text": {
                    "eventAdditionalText": {
                      "event-description": "CHP : Traffic Collision on I-580 Eastbound ramp to CA-24 E (Oakland). Left lane blocked. Expect delays."
                    }
                  }
                }
              ]
            },
            "event-element-location": {
              "event-location-type": {
                "event-location-type-link": {
                  "event-location-type-area": "CA001",
                  "link-road-designator": "I-580 E",
                  "link-from-road": "CA-24 E",
                  "link-to-road": null,
                  "link-from-city": "Oakland",
                  "link-to-city": null,
                  "link-primary-location": {
                    "event-location-coordinates-latitude": "37.825706",
                    "event-location-coordinates-longitude": "-122.274818"
                  }
                }
              }
            },
            "event-element-times": {
              "update-time": "2022-05-10T16:41:10.91330",
              "valid-period": {
                "event-timeline-estimated-duration": "26.5"
              },
              "start-time": "2022-05-10T16:39:00.00000",
              "cleared-time": null,
              "utc-offset": "-0700"
            },
            "event-element-source": {
              "event-organization-reported-identifier": "1003"
            }
          }
        },
        "EventImpact": "Moderate",
        "RoadClosed": "false",
        "ivr-eventStatus": "2",
        "ivr-eventClass": "2",
        "ivr-eventDirection": "Eastbound",
        "ivr-lastUpdateDttm": "2022-05-10T16:41:10.91330",
        "ivr-article": "ramp to",
        "ivr-county": "Alameda",
        "ivr-laneStatus": "blocked",
        "ivr-totalLanes": "Left lane",
        "ivr-genOtherText": "Expect delays",
        "SourceEventID": "220510GG01523",
        "EventSourceName": "CHP",
        "ivr-completeFlag": "1"
      }
    },
    {
      "status": "ACTIVE",
      "headline": "CHP : Disabled vehicle on CA-237 Eastbound west of N Fair Oaks Ave (Sunnyvale). Lane affected. Expect delays.",
      "event_type": "INCIDENT",
      "event_subtypes": {
        "event_subtype": "Disabled vehicle"
      },
      "severity": "Moderate",
      "created": "2022-05-10T23:30Z",
      "updated": "2022-05-10T23:30Z",
      "areas": {
        "area": {
          "name": "Santa Clara",
          "id": "5393021",
          "link": {
            "@rel": "self",
            "@href": "http://geonames.org/5393021/"
          }
        }
      },
      "geography": {
        "crs": {
          "type": "name",
          "properties": {
            "name": "urn:ogc:def:crs:EPSG::4326"
          }
        },
        "type": "Point",
        "coordinates": [
          -122.013184,
          37.405925
        ]
      },
      "source_type": {
        "@xmlns": "http://511.org/open511-extensions",
        "#text": "CHP"
      },
      "source_id": {
        "@xmlns": "http://511.org/open511-extensions",
        "#text": "220510GG01583"
      },
      "roads": [
        {
          "name": "CA-237 E",
          "from": "N Fair Oaks Ave",
          "direction": "Eastbound",
          "state": "SOME_LANES_CLOSED",
          "lane_type": {
            "@xmlns": "http://511.org/open511-extensions",
            "#text": "Lane"
          },
          "lane_status": {
            "@xmlns": "http://511.org/open511-extensions",
            "#text": "affected"
          },
          "road_advisory": {
            "@xmlns": "http://511.org/open511-extensions",
            "#text": "Expect delays"
          },
          "article": {
            "@xmlns": "http://511.org/open511-extensions",
            "#text": "west of"
          }
        }
      ],
      "schedule": {
        "intervals": [
          "2022-05-10T23:30Z/"
        ]
      },
      "extension": {
        "message-header": {
          "event-message-time-stamp": "2022-05-10T16:49:07.13136"
        },
        "event-reference": {
          "event-identifier": "902374"
        },
        "event-status": "new",
        "details": {
          "eventElementDetails": {
            "event-element-sequence": "4",
            "event-element-description": {
              "eventDescription": [
                {
                  "event-phrase": {
                    "eventType": {
                      "incident": "Disabled vehicle"
                    }
                  }
                },
                {
                  "event-advice": "(unknown)"
                },
                {
                  "event-additional-text": {
                    "eventAdditionalText": {
                      "event-description": "CHP : Disabled vehicle on CA-237 Eastbound west of N Fair Oaks Ave (Sunnyvale). Lane affected. Expect delays."
                    }
                  }
                }
              ]
            },
            "event-element-location": {
              "event-location-type": {
                "event-location-type-link": {
                  "event-location-type-area": "CA085",
                  "link-road-designator": "CA-237 E",
                  "link-from-road": "N Fair Oaks Ave",
                  "link-to-road": null,
                  "link-from-city": "Sunnyvale",
                  "link-to-city": null,
                  "link-primary-location": {
                    "event-location-coordinates-latitude": "37.405925",
                    "event-location-coordinates-longitude": "-122.013184"
                  }
                }
              }
            },
            "event-element-times": {
              "update-time": "2022-05-10T16:30:44.17990",
              "valid-period": {
                "event-timeline-estimated-duration": "30.199999999999996"
              },
              "start-time": "2022-05-10T16:30:44.00000",
              "cleared-time": null,
              "utc-offset": "-0700"
            },
            "event-element-source": {
              "event-organization-reported-identifier": "1003"
            }
          }
        },
        "EventImpact": "Moderate",
        "RoadClosed": "false",
        "ivr-eventStatus": "2",
        "ivr-eventClass": "2",
        "ivr-eventDirection": "Eastbound",
        "ivr-lastUpdateDttm": "2022-05-10T16:30:44.17990",
        "ivr-article": "west of",
        "ivr-county": "Santa Clara",
        "ivr-laneStatus": "affected",
        "ivr-totalLanes": "Lane",
        "ivr-genOtherText": "Expect delays",
        "SourceEventID": "220510GG01583",
        "EventSourceName": "CHP",
        "ivr-completeFlag": "1"
      }
    },
    {
      "status": "ACTIVE",
      "headline": "CHP : Traffic Collision on I-680 Southbound south of Livorna Rd (Alamo). Left lanes blocked. Expect delays.",
      "event_type": "INCIDENT",
      "event_subtypes": {
        "event_subtype": "Traffic Collision"
      },
      "severity": "Moderate",
      "created": "2022-05-10T23:34Z",
      "updated": "2022-05-10T23:41Z",
      "areas": {
        "area": {
          "name": "Contra Costa",
          "id": "5339268",
          "link": {
            "@rel": "self",
            "@href": "http://geonames.org/5339268/"
          }
        }
      },
      "geography": {
        "crs": {
          "type": "name",
          "properties": {
            "name": "urn:ogc:def:crs:EPSG::4326"
          }
        },
        "type": "Point",
        "coordinates": [
          -122.035614,
          37.863346
        ]
      },
      "source_type": {
        "@xmlns": "http://511.org/open511-extensions",
        "#text": "CHP"
      },
      "source_id": {
        "@xmlns": "http://511.org/open511-extensions",
        "#text": "220510GG01591"
      },
      "roads": [
        {
          "name": "I-680 S",
          "from": "Livorna Rd",
          "direction": "Southbound",
          "state": "SOME_LANES_CLOSED",
          "lane_type": {
            "@xmlns": "http://511.org/open511-extensions",
            "#text": "Left lanes"
          },
          "lane_status": {
            "@xmlns": "http://511.org/open511-extensions",
            "#text": "blocked"
          },
          "road_advisory": {
            "@xmlns": "http://511.org/open511-extensions",
            "#text": "Expect delays"
          },
          "article": {
            "@xmlns": "http://511.org/open511-extensions",
            "#text": "south of"
          }
        }
      ],
      "schedule": {
        "intervals": [
          "2022-05-10T23:41Z/"
        ]
      },
      "extension": {
        "message-header": {
          "event-message-time-stamp": "2022-05-10T16:49:07.13136"
        },
        "event-reference": {
          "event-identifier": "902375"
        },
        "event-status": "new",
        "details": {
          "eventElementDetails": {
            "event-element-sequence": "4",
            "event-element-description": {
              "eventDescription": [
                {
                  "event-phrase": {
                    "eventType": {
                      "incident": "Traffic Collision"
                    }
                  }
                },
                {
                  "event-advice": "(unknown)"
                },
                {
                  "event-additional-text": {
                    "eventAdditionalText": {
                      "event-description": "CHP : Traffic Collision on I-680 Southbound south of Livorna Rd (Alamo). Left lanes blocked. Expect delays."
                    }
                  }
                }
              ]
            },
            "event-element-location": {
              "event-location-type": {
                "event-location-type-link": {
                  "event-location-type-area": "CA013",
                  "link-road-designator": "I-680 S",
                  "link-from-road": "Livorna Rd",
                  "link-to-road": null,
                  "link-from-city": "Alamo",
                  "link-to-city": null,
                  "link-primary-location": {
                    "event-location-coordinates-latitude": "37.863346",
                    "event-location-coordinates-longitude": "-122.035614"
                  }
                }
              }
            },
            "event-element-times": {
              "update-time": "2022-05-10T16:41:59.28280",
              "valid-period": {
                "event-timeline-estimated-duration": "34"
              },
              "start-time": "2022-05-10T16:41:00.00000",
              "cleared-time": null,
              "utc-offset": "-0700"
            },
            "event-element-source": {
              "event-organization-reported-identifier": "1003"
            }
          }
        },
        "EventImpact": "Moderate",
        "RoadClosed": "false",
        "ivr-eventStatus": "2",
        "ivr-eventClass": "2",
        "ivr-eventDirection": "Southbound",
        "ivr-lastUpdateDttm": "2022-05-10T16:41:59.28280",
        "ivr-article": "south of",
        "ivr-county": "Contra Costa",
        "ivr-laneStatus": "blocked",
        "ivr-totalLanes": "Left lanes",
        "ivr-genOtherText": "Expect delays",
        "SourceEventID": "220510GG01591",
        "EventSourceName": "CHP",
        "ivr-completeFlag": "1"
      }
    },
    {
      "status": "ACTIVE",
      "headline": "CHP : Traffic Hazard on I-80 Eastbound west of Treasure Island Rd (San Francisco). Lane affected. Expect delays.",
      "event_type": "INCIDENT",
      "event_subtypes": {
        "event_subtype": "Traffic Hazard"
      },
      "severity": "Major",
      "created": "2022-05-10T23:36Z",
      "updated": "2022-05-10T23:38Z",
      "areas": {
        "area": {
          "name": "San Francisco",
          "id": "5391997",
          "link": {
            "@rel": "self",
            "@href": "http://geonames.org/5391997/"
          }
        }
      },
      "geography": {
        "crs": {
          "type": "name",
          "properties": {
            "name": "urn:ogc:def:crs:EPSG::4326"
          }
        },
        "type": "Point",
        "coordinates": [
          -122.366974,
          37.808253
        ]
      },
      "source_type": {
        "@xmlns": "http://511.org/open511-extensions",
        "#text": "CHP"
      },
      "source_id": {
        "@xmlns": "http://511.org/open511-extensions",
        "#text": "220510GG01593"
      },
      "roads": [
        {
          "name": "I-80 E",
          "from": "Treasure Island Rd",
          "direction": "Eastbound",
          "state": "SOME_LANES_CLOSED",
          "lane_type": {
            "@xmlns": "http://511.org/open511-extensions",
            "#text": "Lane"
          },
          "lane_status": {
            "@xmlns": "http://511.org/open511-extensions",
            "#text": "affected"
          },
          "road_advisory": {
            "@xmlns": "http://511.org/open511-extensions",
            "#text": "Expect delays"
          },
          "article": {
            "@xmlns": "http://511.org/open511-extensions",
            "#text": "west of"
          }
        }
      ],
      "schedule": {
        "intervals": [
          "2022-05-10T23:38Z/"
        ]
      },
      "extension": {
        "message-header": {
          "event-message-time-stamp": "2022-05-10T16:49:07.13136"
        },
        "event-reference": {
          "event-identifier": "902377"
        },
        "event-status": "new",
        "details": {
          "eventElementDetails": {
            "event-element-sequence": "4",
            "event-element-description": {
              "eventDescription": [
                {
                  "event-phrase": {
                    "eventType": {
                      "incident": "Traffic Hazard"
                    }
                  }
                },
                {
                  "event-advice": "(unknown)"
                },
                {
                  "event-additional-text": {
                    "eventAdditionalText": {
                      "event-description": "CHP : Traffic Hazard on I-80 Eastbound west of Treasure Island Rd (San Francisco). Lane affected. Expect delays."
                    }
                  }
                }
              ]
            },
            "event-element-location": {
              "event-location-type": {
                "event-location-type-link": {
                  "event-location-type-area": "CA075",
                  "link-road-designator": "I-80 E",
                  "link-from-road": "Treasure Island Rd",
                  "link-to-road": null,
                  "link-from-city": "San Francisco",
                  "link-to-city": null,
                  "link-primary-location": {
                    "event-location-coordinates-latitude": "37.808253",
                    "event-location-coordinates-longitude": "-122.366974"
                  }
                }
              }
            },
            "event-element-times": {
              "update-time": "2022-05-10T16:38:00.20060",
              "valid-period": {
                "event-timeline-estimated-duration": "49"
              },
              "start-time": "2022-05-10T16:38:00.00000",
              "cleared-time": null,
              "utc-offset": "-0700"
            },
            "event-element-source": {
              "event-organization-reported-identifier": "1003"
            }
          }
        },
        "EventImpact": "Major",
        "RoadClosed": "false",
        "ivr-eventStatus": "2",
        "ivr-eventClass": "3",
        "ivr-eventDirection": "Eastbound",
        "ivr-lastUpdateDttm": "2022-05-10T16:38:00.20060",
        "ivr-article": "west of",
        "ivr-county": "San Francisco",
        "ivr-laneStatus": "affected",
        "ivr-totalLanes": "Lane",
        "ivr-genOtherText": "Expect delays",
        "SourceEventID": "220510GG01593",
        "EventSourceName": "CHP",
        "ivr-completeFlag": "1"
      }
    },
    {
      "status": "ACTIVE",
      "headline": "CHP : Traffic Hazard on CA-17 Southbound north of CA-85 N (Los Gatos). 2nd lane from the left affected. Expect delays.",
      "event_type": "INCIDENT",
      "event_subtypes": {
        "event_subtype": "Traffic Hazard"
      },
      "severity": "Moderate",
      "created": "2022-05-10T23:39Z",
      "updated": "2022-05-10T23:39Z",
      "areas": {
        "area": {
          "name": "Santa Clara",
          "id": "5393021",
          "link": {
            "@rel": "self",
            "@href": "http://geonames.org/5393021/"
          }
        }
      },
      "geography": {
        "crs": {
          "type": "name",
          "properties": {
            "name": "urn:ogc:def:crs:EPSG::4326"
          }
        },
        "type": "Point",
        "coordinates": [
          -121.951075,
          37.262292
        ]
      },
      "source_type": {
        "@xmlns": "http://511.org/open511-extensions",
        "#text": "CHP"
      },
      "source_id": {
        "@xmlns": "http://511.org/open511-extensions",
        "#text": "220510GG01597"
      },
      "roads": [
        {
          "name": "CA-17 S",
          "from": "CA-85 N",
          "direction": "Southbound",
          "state": "SOME_LANES_CLOSED",
          "lane_type": {
            "@xmlns": "http://511.org/open511-extensions",
            "#text": "2nd lane from the left"
          },
          "lane_status": {
            "@xmlns": "http://511.org/open511-extensions",
            "#text": "affected"
          },
          "road_advisory": {
            "@xmlns": "http://511.org/open511-extensions",
            "#text": "Expect delays"
          },
          "article": {
            "@xmlns": "http://511.org/open511-extensions",
            "#text": "north of"
          }
        }
      ],
      "schedule": {
        "intervals": [
          "2022-05-10T23:39Z/"
        ]
      },
      "extension": {
        "message-header": {
          "event-message-time-stamp": "2022-05-10T16:49:07.13136"
        },
        "event-reference": {
          "event-identifier": "902378"
        },
        "event-status": "new",
        "details": {
          "eventElementDetails": {
            "event-element-sequence": "4",
            "event-element-description": {
              "eventDescription": [
                {
                  "event-phrase": {
                    "eventType": {
                      "incident": "Traffic Hazard"
                    }
                  }
                },
                {
                  "event-advice": "(unknown)"
                },
                {
                  "event-additional-text": {
                    "eventAdditionalText": {
                      "event-description": "CHP : Traffic Hazard on CA-17 Southbound north of CA-85 N (Los Gatos). 2nd lane from the left affected. Expect delays."
                    }
                  }
                }
              ]
            },
            "event-element-location": {
              "event-location-type": {
                "event-location-type-link": {
                  "event-location-type-area": "CA085",
                  "link-road-designator": "CA-17 S",
                  "link-from-road": "CA-85 N",
                  "link-to-road": null,
                  "link-from-city": "Los Gatos",
                  "link-to-city": null,
                  "link-primary-location": {
                    "event-location-coordinates-latitude": "37.262292",
                    "event-location-coordinates-longitude": "-121.951075"
                  }
                }
              }
            },
            "event-element-times": {
              "update-time": "2022-05-10T16:39:02.29320",
              "valid-period": {
                "event-timeline-estimated-duration": "28"
              },
              "start-time": "2022-05-10T16:39:02.00000",
              "cleared-time": null,
              "utc-offset": "-0700"
            },
            "event-element-source": {
              "event-organization-reported-identifier": "1003"
            }
          }
        },
        "EventImpact": "Moderate",
        "RoadClosed": "false",
        "ivr-eventStatus": "2",
        "ivr-eventClass": "2",
        "ivr-eventDirection": "Southbound",
        "ivr-lastUpdateDttm": "2022-05-10T16:39:02.29320",
        "ivr-article": "north of",
        "ivr-county": "Santa Clara",
        "ivr-laneStatus": "affected",
        "ivr-totalLanes": "2nd lane from the left",
        "ivr-genOtherText": "Expect delays",
        "SourceEventID": "220510GG01597",
        "EventSourceName": "CHP",
        "ivr-completeFlag": "1"
      }
    },
    {
      "status": "ACTIVE",
      "headline": "CHP : Traffic Collision on I-580 Westbound east of I-680 N (Pleasanton). Lane affected. Expect delays.",
      "event_type": "INCIDENT",
      "event_subtypes": {
        "event_subtype": "Traffic Collision"
      },
      "severity": "Moderate",
      "created": "2022-05-10T23:42Z",
      "updated": "2022-05-10T23:43Z",
      "areas": {
        "area": {
          "name": "Alameda",
          "id": "5322745",
          "link": {
            "@rel": "self",
            "@href": "http://geonames.org/5322745/"
          }
        }
      },
      "geography": {
        "crs": {
          "type": "name",
          "properties": {
            "name": "urn:ogc:def:crs:EPSG::4326"
          }
        },
        "type": "Point",
        "coordinates": [
          -121.917091,
          37.701987
        ]
      },
      "source_type": {
        "@xmlns": "http://511.org/open511-extensions",
        "#text": "CHP"
      },
      "source_id": {
        "@xmlns": "http://511.org/open511-extensions",
        "#text": "220510GG01605"
      },
      "roads": [
        {
          "name": "I-580 W",
          "from": "I-680 N",
          "direction": "Westbound",
          "state": "SOME_LANES_CLOSED",
          "lane_type": {
            "@xmlns": "http://511.org/open511-extensions",
            "#text": "Lane"
          },
          "lane_status": {
            "@xmlns": "http://511.org/open511-extensions",
            "#text": "affected"
          },
          "road_advisory": {
            "@xmlns": "http://511.org/open511-extensions",
            "#text": "Expect delays"
          },
          "article": {
            "@xmlns": "http://511.org/open511-extensions",
            "#text": "east of"
          }
        }
      ],
      "schedule": {
        "intervals": [
          "2022-05-10T23:43Z/"
        ]
      },
      "extension": {
        "message-header": {
          "event-message-time-stamp": "2022-05-10T16:49:07.13136"
        },
        "event-reference": {
          "event-identifier": "902380"
        },
        "event-status": "new",
        "details": {
          "eventElementDetails": {
            "event-element-sequence": "4",
            "event-element-description": {
              "eventDescription": [
                {
                  "event-phrase": {
                    "eventType": {
                      "incident": "Traffic Collision"
                    }
                  }
                },
                {
                  "event-advice": "(unknown)"
                },
                {
                  "event-additional-text": {
                    "eventAdditionalText": {
                      "event-description": "CHP : Traffic Collision on I-580 Westbound east of I-680 N (Pleasanton). Lane affected. Expect delays."
                    }
                  }
                }
              ]
            },
            "event-element-location": {
              "event-location-type": {
                "event-location-type-link": {
                  "event-location-type-area": "CA001",
                  "link-road-designator": "I-580 W",
                  "link-from-road": "I-680 N",
                  "link-to-road": null,
                  "link-from-city": "Pleasanton",
                  "link-to-city": null,
                  "link-primary-location": {
                    "event-location-coordinates-latitude": "37.701987",
                    "event-location-coordinates-longitude": "-121.917091"
                  }
                }
              }
            },
            "event-element-times": {
              "update-time": "2022-05-10T16:43:12.59760",
              "valid-period": {
                "event-timeline-estimated-duration": "25"
              },
              "start-time": "2022-05-10T16:43:12.00000",
              "cleared-time": null,
              "utc-offset": "-0700"
            },
            "event-element-source": {
              "event-organization-reported-identifier": "1003"
            }
          }
        },
        "EventImpact": "Moderate",
        "RoadClosed": "false",
        "ivr-eventStatus": "2",
        "ivr-eventClass": "2",
        "ivr-eventDirection": "Westbound",
        "ivr-lastUpdateDttm": "2022-05-10T16:43:12.59760",
        "ivr-article": "east of",
        "ivr-county": "Alameda",
        "ivr-laneStatus": "affected",
        "ivr-totalLanes": "Lane",
        "ivr-genOtherText": "Expect delays",
        "SourceEventID": "220510GG01605",
        "EventSourceName": "CHP",
        "ivr-completeFlag": "1"
      }
    },
    {
      "status": "ACTIVE",
      "headline": "CHP : Residual delays on I-680 Northbound south of N Capitol Ave (San Jose). Off Ramp affected. Expect delays.",
      "event_type": "INCIDENT",
      "event_subtypes": {
        "event_subtype": "Residual delays"
      },
      "severity": "Major",
      "created": "2022-05-10T23:43Z",
      "updated": "2022-05-10T23:43Z",
      "areas": {
        "area": {
          "name": "Santa Clara",
          "id": "5393021",
          "link": {
            "@rel": "self",
            "@href": "http://geonames.org/5393021/"
          }
        }
      },
      "geography": {
        "crs": {
          "type": "name",
          "properties": {
            "name": "urn:ogc:def:crs:EPSG::4326"
          }
        },
        "type": "Point",
        "coordinates": [
          -121.876889,
          37.403618
        ]
      },
      "source_type": {
        "@xmlns": "http://511.org/open511-extensions",
        "#text": "CHP"
      },
      "source_id": {
        "@xmlns": "http://511.org/open511-extensions",
        "#text": "220510GG01609"
      },
      "roads": [
        {
          "name": "I-680 N",
          "from": "N Capitol Ave",
          "direction": "Northbound",
          "state": "SOME_LANES_CLOSED",
          "lane_type": {
            "@xmlns": "http://511.org/open511-extensions",
            "#text": "Off Ramp"
          },
          "lane_status": {
            "@xmlns": "http://511.org/open511-extensions",
            "#text": "affected"
          },
          "road_advisory": {
            "@xmlns": "http://511.org/open511-extensions",
            "#text": "Expect delays"
          },
          "article": {
            "@xmlns": "http://511.org/open511-extensions",
            "#text": "south of"
          }
        }
      ],
      "schedule": {
        "intervals": [
          "2022-05-10T23:43Z/"
        ]
      },
      "extension": {
        "message-header": {
          "event-message-time-stamp": "2022-05-10T16:49:07.13136"
        },
        "event-reference": {
          "event-identifier": "902381"
        },
        "event-status": "new",
        "details": {
          "eventElementDetails": {
            "event-element-sequence": "4",
            "event-element-description": {
              "eventDescription": [
                {
                  "event-phrase": {
                    "eventType": {
                      "incident": "Residual delays"
                    }
                  }
                },
                {
                  "event-advice": "(unknown)"
                },
                {
                  "event-additional-text": {
                    "eventAdditionalText": {
                      "event-description": "CHP : Residual delays on I-680 Northbound south of N Capitol Ave (San Jose). Off Ramp affected. Expect delays."
                    }
                  }
                }
              ]
            },
            "event-element-location": {
              "event-location-type": {
                "event-location-type-link": {
                  "event-location-type-area": "CA085",
                  "link-road-designator": "I-680 N",
                  "link-from-road": "N Capitol Ave",
                  "link-to-road": null,
                  "link-from-city": "San Jose",
                  "link-to-city": null,
                  "link-primary-location": {
                    "event-location-coordinates-latitude": "37.403618",
                    "event-location-coordinates-longitude": "-121.876889"
                  }
                }
              }
            },
            "event-element-times": {
              "update-time": "2022-05-10T16:43:51.04250",
              "valid-period": {
                "event-timeline-estimated-duration": "50.5"
              },
              "start-time": "2022-05-10T16:43:00.00000",
              "cleared-time": null,
              "utc-offset": "-0700"
            },
            "event-element-source": {
              "event-organization-reported-identifier": "1003"
            }
          }
        },
        "EventImpact": "Major",
        "RoadClosed": "false",
        "ivr-eventStatus": "2",
        "ivr-eventClass": "3",
        "ivr-eventDirection": "Northbound",
        "ivr-lastUpdateDttm": "2022-05-10T16:43:51.04250",
        "ivr-article": "south of",
        "ivr-county": "Santa Clara",
        "ivr-laneStatus": "affected",
        "ivr-totalLanes": "Off Ramp",
        "ivr-genOtherText": "Expect delays",
        "SourceEventID": "220510GG01609",
        "EventSourceName": "CHP",
        "ivr-completeFlag": "1"
      }
    },
    {
      "status": "ACTIVE",
      "headline": "CHP : Disabled vehicle on US-101 Northbound north of Coyote Creek Golf Dr (San Jose). Lane affected. Expect delays.",
      "event_type": "INCIDENT",
      "event_subtypes": {
        "event_subtype": "Disabled vehicle"
      },
      "severity": "Moderate",
      "created": "2022-05-10T23:45Z",
      "updated": "2022-05-10T23:45Z",
      "areas": {
        "area": {
          "name": "Santa Clara",
          "id": "5393021",
          "link": {
            "@rel": "self",
            "@href": "http://geonames.org/5393021/"
          }
        }
      },
      "geography": {
        "crs": {
          "type": "name",
          "properties": {
            "name": "urn:ogc:def:crs:EPSG::4326"
          }
        },
        "type": "Point",
        "coordinates": [
          -121.688818,
          37.187836
        ]
      },
      "source_type": {
        "@xmlns": "http://511.org/open511-extensions",
        "#text": "CHP"
      },
      "source_id": {
        "@xmlns": "http://511.org/open511-extensions",
        "#text": "220510MY00248"
      },
      "roads": [
        {
          "name": "US-101 N",
          "from": "Coyote Creek Golf Dr",
          "direction": "Northbound",
          "state": "SOME_LANES_CLOSED",
          "lane_type": {
            "@xmlns": "http://511.org/open511-extensions",
            "#text": "Lane"
          },
          "lane_status": {
            "@xmlns": "http://511.org/open511-extensions",
            "#text": "affected"
          },
          "road_advisory": {
            "@xmlns": "http://511.org/open511-extensions",
            "#text": "Expect delays"
          },
          "article": {
            "@xmlns": "http://511.org/open511-extensions",
            "#text": "north of"
          }
        }
      ],
      "schedule": {
        "intervals": [
          "2022-05-10T23:45Z/"
        ]
      },
      "extension": {
        "message-header": {
          "event-message-time-stamp": "2022-05-10T16:49:07.13136"
        },
        "event-reference": {
          "event-identifier": "902382"
        },
        "event-status": "new",
        "details": {
          "eventElementDetails": {
            "event-element-sequence": "4",
            "event-element-description": {
              "eventDescription": [
                {
                  "event-phrase": {
                    "eventType": {
                      "incident": "Disabled vehicle"
                    }
                  }
                },
                {
                  "event-advice": "(unknown)"
                },
                {
                  "event-additional-text": {
                    "eventAdditionalText": {
                      "event-description": "CHP : Disabled vehicle on US-101 Northbound north of Coyote Creek Golf Dr (San Jose). Lane affected. Expect delays."
                    }
                  }
                }
              ]
            },
            "event-element-location": {
              "event-location-type": {
                "event-location-type-link": {
                  "event-location-type-area": "CA085",
                  "link-road-designator": "US-101 N",
                  "link-from-road": "Coyote Creek Golf Dr",
                  "link-to-road": null,
                  "link-from-city": "San Jose",
                  "link-to-city": null,
                  "link-primary-location": {
                    "event-location-coordinates-latitude": "37.187836",
                    "event-location-coordinates-longitude": "-121.688818"
                  }
                }
              }
            },
            "event-element-times": {
              "update-time": "2022-05-10T16:45:16.80870",
              "valid-period": {
                "event-timeline-estimated-duration": "35.2"
              },
              "start-time": "2022-05-10T16:45:16.00000",
              "cleared-time": null,
              "utc-offset": "-0700"
            },
            "event-element-source": {
              "event-organization-reported-identifier": "1003"
            }
          }
        },
        "EventImpact": "Moderate",
        "RoadClosed": "false",
        "ivr-eventStatus": "2",
        "ivr-eventClass": "2",
        "ivr-eventDirection": "Northbound",
        "ivr-lastUpdateDttm": "2022-05-10T16:45:16.80870",
        "ivr-article": "north of",
        "ivr-county": "Santa Clara",
        "ivr-laneStatus": "affected",
        "ivr-totalLanes": "Lane",
        "ivr-genOtherText": "Expect delays",
        "SourceEventID": "220510MY00248",
        "EventSourceName": "CHP",
        "ivr-completeFlag": "1"
      }
    },
    {
      "status": "ACTIVE",
      "headline": "CHP : Disabled vehicle on CA-85 Southbound south of Stevens Creek Blvd (Cupertino). Lane affected. Expect delays.",
      "event_type": "INCIDENT",
      "event_subtypes": {
        "event_subtype": "Disabled vehicle"
      },
      "severity": "Moderate",
      "created": "2022-05-10T23:46Z",
      "updated": "2022-05-10T23:48Z",
      "areas": {
        "area": {
          "name": "Santa Clara",
          "id": "5393021",
          "link": {
            "@rel": "self",
            "@href": "http://geonames.org/5393021/"
          }
        }
      },
      "geography": {
        "crs": {
          "type": "name",
          "properties": {
            "name": "urn:ogc:def:crs:EPSG::4326"
          }
        },
        "type": "Point",
        "coordinates": [
          -122.05086,
          37.325981
        ]
      },
      "source_type": {
        "@xmlns": "http://511.org/open511-extensions",
        "#text": "CHP"
      },
      "source_id": {
        "@xmlns": "http://511.org/open511-extensions",
        "#text": "220510GG01615"
      },
      "roads": [
        {
          "name": "CA-85 S",
          "from": "Stevens Creek Blvd",
          "direction": "Southbound",
          "state": "SOME_LANES_CLOSED",
          "lane_type": {
            "@xmlns": "http://511.org/open511-extensions",
            "#text": "Lane"
          },
          "lane_status": {
            "@xmlns": "http://511.org/open511-extensions",
            "#text": "affected"
          },
          "road_advisory": {
            "@xmlns": "http://511.org/open511-extensions",
            "#text": "Expect delays"
          },
          "article": {
            "@xmlns": "http://511.org/open511-extensions",
            "#text": "south of"
          }
        }
      ],
      "schedule": {
        "intervals": [
          "2022-05-10T23:48Z/"
        ]
      },
      "extension": {
        "message-header": {
          "event-message-time-stamp": "2022-05-10T16:49:07.13136"
        },
        "event-reference": {
          "event-identifier": "902383"
        },
        "event-status": "new",
        "details": {
          "eventElementDetails": {
            "event-element-sequence": "4",
            "event-element-description": {
              "eventDescription": [
                {
                  "event-phrase": {
                    "eventType": {
                      "incident": "Disabled vehicle"
                    }
                  }
                },
                {
                  "event-advice": "(unknown)"
                },
                {
                  "event-additional-text": {
                    "eventAdditionalText": {
                      "event-description": "CHP : Disabled vehicle on CA-85 Southbound south of Stevens Creek Blvd (Cupertino). Lane affected. Expect delays."
                    }
                  }
                }
              ]
            },
            "event-element-location": {
              "event-location-type": {
                "event-location-type-link": {
                  "event-location-type-area": "CA085",
                  "link-road-designator": "CA-85 S",
                  "link-from-road": "Stevens Creek Blvd",
                  "link-to-road": null,
                  "link-from-city": "Cupertino",
                  "link-to-city": null,
                  "link-primary-location": {
                    "event-location-coordinates-latitude": "37.325981",
                    "event-location-coordinates-longitude": "-122.05086"
                  }
                }
              }
            },
            "event-element-times": {
              "update-time": "2022-05-10T16:48:23.66990",
              "valid-period": {
                "event-timeline-estimated-duration": "30.199999999999996"
              },
              "start-time": "2022-05-10T16:48:23.00000",
              "cleared-time": null,
              "utc-offset": "-0700"
            },
            "event-element-source": {
              "event-organization-reported-identifier": "1003"
            }
          }
        },
        "EventImpact": "Moderate",
        "RoadClosed": "false",
        "ivr-eventStatus": "2",
        "ivr-eventClass": "2",
        "ivr-eventDirection": "Southbound",
        "ivr-lastUpdateDttm": "2022-05-10T16:48:23.66990",
        "ivr-article": "south of",
        "ivr-county": "Santa Clara",
        "ivr-laneStatus": "affected",
        "ivr-totalLanes": "Lane",
        "ivr-genOtherText": "Expect delays",
        "SourceEventID": "220510GG01615",
        "EventSourceName": "CHP",
        "ivr-completeFlag": "1"
      }
    },
    {
      "status": "ACTIVE",
      "headline": "CHP : Traffic Hazard on I-580 Westbound east of CA-24 E (Oakland). Lane affected. Expect delays.",
      "event_type": "INCIDENT",
      "event_subtypes": {
        "event_subtype": "Traffic Hazard"
      },
      "severity": "Moderate",
      "created": "2022-05-10T23:46Z",
      "updated": "2022-05-10T23:46Z",
      "areas": {
        "area": {
          "name": "Alameda",
          "id": "5322745",
          "link": {
            "@rel": "self",
            "@href": "http://geonames.org/5322745/"
          }
        }
      },
      "geography": {
        "crs": {
          "type": "name",
          "properties": {
            "name": "urn:ogc:def:crs:EPSG::4326"
          }
        },
        "type": "Point",
        "coordinates": [
          -122.267975,
          37.824282
        ]
      },
      "source_type": {
        "@xmlns": "http://511.org/open511-extensions",
        "#text": "CHP"
      },
      "source_id": {
        "@xmlns": "http://511.org/open511-extensions",
        "#text": "220510GG01616"
      },
      "roads": [
        {
          "name": "I-580 W",
          "from": "CA-24 E",
          "direction": "Westbound",
          "state": "SOME_LANES_CLOSED",
          "lane_type": {
            "@xmlns": "http://511.org/open511-extensions",
            "#text": "Lane"
          },
          "lane_status": {
            "@xmlns": "http://511.org/open511-extensions",
            "#text": "affected"
          },
          "road_advisory": {
            "@xmlns": "http://511.org/open511-extensions",
            "#text": "Expect delays"
          },
          "article": {
            "@xmlns": "http://511.org/open511-extensions",
            "#text": "east of"
          }
        }
      ],
      "schedule": {
        "intervals": [
          "2022-05-10T23:46Z/"
        ]
      },
      "extension": {
        "message-header": {
          "event-message-time-stamp": "2022-05-10T16:49:07.13136"
        },
        "event-reference": {
          "event-identifier": "902384"
        },
        "event-status": "new",
        "details": {
          "eventElementDetails": {
            "event-element-sequence": "4",
            "event-element-description": {
              "eventDescription": [
                {
                  "event-phrase": {
                    "eventType": {
                      "incident": "Traffic Hazard"
                    }
                  }
                },
                {
                  "event-advice": "(unknown)"
                },
                {
                  "event-additional-text": {
                    "eventAdditionalText": {
                      "event-description": "CHP : Traffic Hazard on I-580 Westbound east of CA-24 E (Oakland). Lane affected. Expect delays."
                    }
                  }
                }
              ]
            },
            "event-element-location": {
              "event-location-type": {
                "event-location-type-link": {
                  "event-location-type-area": "CA001",
                  "link-road-designator": "I-580 W",
                  "link-from-road": "CA-24 E",
                  "link-to-road": null,
                  "link-from-city": "Oakland",
                  "link-to-city": null,
                  "link-primary-location": {
                    "event-location-coordinates-latitude": "37.824282",
                    "event-location-coordinates-longitude": "-122.267975"
                  }
                }
              }
            },
            "event-element-times": {
              "update-time": "2022-05-10T16:46:19.01060",
              "valid-period": {
                "event-timeline-estimated-duration": "26.5"
              },
              "start-time": "2022-05-10T16:46:19.00000",
              "cleared-time": null,
              "utc-offset": "-0700"
            },
            "event-element-source": {
              "event-organization-reported-identifier": "1003"
            }
          }
        },
        "EventImpact": "Moderate",
        "RoadClosed": "false",
        "ivr-eventStatus": "2",
        "ivr-eventClass": "2",
        "ivr-eventDirection": "Westbound",
        "ivr-lastUpdateDttm": "2022-05-10T16:46:19.01060",
        "ivr-article": "east of",
        "ivr-county": "Alameda",
        "ivr-laneStatus": "affected",
        "ivr-totalLanes": "Lane",
        "ivr-genOtherText": "Expect delays",
        "SourceEventID": "220510GG01616",
        "EventSourceName": "CHP",
        "ivr-completeFlag": "1"
      }
    },
    {
      "status": "ACTIVE",
      "headline": "CHP : Traffic Hazard on CA-37 Eastbound east of Atherton Ave (Novato). Right shoulder affected. Expect delays.",
      "event_type": "INCIDENT",
      "event_subtypes": {
        "event_subtype": "Traffic Hazard"
      },
      "severity": "Major",
      "created": "2022-05-10T23:48Z",
      "updated": "2022-05-10T23:48Z",
      "areas": {
        "area": {
          "name": "Marin",
          "id": "5370468",
          "link": {
            "@rel": "self",
            "@href": "http://geonames.org/5370468/"
          }
        }
      },
      "geography": {
        "crs": {
          "type": "name",
          "properties": {
            "name": "urn:ogc:def:crs:EPSG::4326"
          }
        },
        "type": "Point",
        "coordinates": [
          -122.514094,
          38.103193
        ]
      },
      "source_type": {
        "@xmlns": "http://511.org/open511-extensions",
        "#text": "CHP"
      },
      "source_id": {
        "@xmlns": "http://511.org/open511-extensions",
        "#text": "220510GG01625"
      },
      "roads": [
        {
          "name": "CA-37 E",
          "from": "Atherton Ave",
          "direction": "Eastbound",
          "state": "SOME_LANES_CLOSED",
          "lane_type": {
            "@xmlns": "http://511.org/open511-extensions",
            "#text": "Right shoulder"
          },
          "lane_status": {
            "@xmlns": "http://511.org/open511-extensions",
            "#text": "affected"
          },
          "road_advisory": {
            "@xmlns": "http://511.org/open511-extensions",
            "#text": "Expect delays"
          },
          "article": {
            "@xmlns": "http://511.org/open511-extensions",
            "#text": "east of"
          }
        }
      ],
      "schedule": {
        "intervals": [
          "2022-05-10T23:48Z/"
        ]
      },
      "extension": {
        "message-header": {
          "event-message-time-stamp": "2022-05-10T16:49:07.13136"
        },
        "event-reference": {
          "event-identifier": "902385"
        },
        "event-status": "new",
        "details": {
          "eventElementDetails": {
            "event-element-sequence": "4",
            "event-element-description": {
              "eventDescription": [
                {
                  "event-phrase": {
                    "eventType": {
                      "incident": "Traffic Hazard"
                    }
                  }
                },
                {
                  "event-advice": "(unknown)"
                },
                {
                  "event-additional-text": {
                    "eventAdditionalText": {
                      "event-description": "CHP : Traffic Hazard on CA-37 Eastbound east of Atherton Ave (Novato). Right shoulder affected. Expect delays."
                    }
                  }
                }
              ]
            },
            "event-element-location": {
              "event-location-type": {
                "event-location-type-link": {
                  "event-location-type-area": "CA041",
                  "link-road-designator": "CA-37 E",
                  "link-from-road": "Atherton Ave",
                  "link-to-road": null,
                  "link-from-city": "Novato",
                  "link-to-city": null,
                  "link-primary-location": {
                    "event-location-coordinates-latitude": "38.103193",
                    "event-location-coordinates-longitude": "-122.514094"
                  }
                }
              }
            },
            "event-element-times": {
              "update-time": "2022-05-10T16:48:23.15300",
              "valid-period": {
                "event-timeline-estimated-duration": "50.5"
              },
              "start-time": "2022-05-10T16:48:23.00000",
              "cleared-time": null,
              "utc-offset": "-0700"
            },
            "event-element-source": {
              "event-organization-reported-identifier": "1003"
            }
          }
        },
        "EventImpact": "Major",
        "RoadClosed": "false",
        "ivr-eventStatus": "2",
        "ivr-eventClass": "3",
        "ivr-eventDirection": "Eastbound",
        "ivr-lastUpdateDttm": "2022-05-10T16:48:23.15300",
        "ivr-article": "east of",
        "ivr-county": "Marin",
        "ivr-laneStatus": "affected",
        "ivr-totalLanes": "Right shoulder",
        "ivr-genOtherText": "Expect delays",
        "SourceEventID": "220510GG01625",
        "EventSourceName": "CHP",
        "ivr-completeFlag": "1"
      }
    },
    {
      "status": "ACTIVE",
      "headline": "CHP : Traffic Collision on I-280 Southbound north of Magdalena Ave (Los Altos). Center Divider affected. Expect delays.",
      "event_type": "INCIDENT",
      "event_subtypes": {
        "event_subtype": "Traffic Collision"
      },
      "severity": "Minor",
      "created": "2022-05-10T23:48Z",
      "updated": "2022-05-10T23:48Z",
      "areas": {
        "area": {
          "name": "Santa Clara",
          "id": "5393021",
          "link": {
            "@rel": "self",
            "@href": "http://geonames.org/5393021/"
          }
        }
      },
      "geography": {
        "crs": {
          "type": "name",
          "properties": {
            "name": "urn:ogc:def:crs:EPSG::4326"
          }
        },
        "type": "Point",
        "coordinates": [
          -122.113546,
          37.355142
        ]
      },
      "source_type": {
        "@xmlns": "http://511.org/open511-extensions",
        "#text": "CHP"
      },
      "source_id": {
        "@xmlns": "http://511.org/open511-extensions",
        "#text": "220510GG01626"
      },
      "roads": [
        {
          "name": "I-280 S",
          "from": "Magdalena Ave",
          "direction": "Southbound",
          "state": "SOME_LANES_CLOSED",
          "lane_type": {
            "@xmlns": "http://511.org/open511-extensions",
            "#text": "Center Divider"
          },
          "lane_status": {
            "@xmlns": "http://511.org/open511-extensions",
            "#text": "affected"
          },
          "road_advisory": {
            "@xmlns": "http://511.org/open511-extensions",
            "#text": "Expect delays"
          },
          "article": {
            "@xmlns": "http://511.org/open511-extensions",
            "#text": "north of"
          }
        }
      ],
      "schedule": {
        "intervals": [
          "2022-05-10T23:48Z/"
        ]
      },
      "extension": {
        "message-header": {
          "event-message-time-stamp": "2022-05-10T16:49:07.13136"
        },
        "event-reference": {
          "event-identifier": "902386"
        },
        "event-status": "new",
        "details": {
          "eventElementDetails": {
            "event-element-sequence": "4",
            "event-element-description": {
              "eventDescription": [
                {
                  "event-phrase": {
                    "eventType": {
                      "incident": "Traffic Collision"
                    }
                  }
                },
                {
                  "event-advice": "(unknown)"
                },
                {
                  "event-additional-text": {
                    "eventAdditionalText": {
                      "event-description": "CHP : Traffic Collision on I-280 Southbound north of Magdalena Ave (Los Altos). Center Divider affected. Expect delays."
                    }
                  }
                }
              ]
            },
            "event-element-location": {
              "event-location-type": {
                "event-location-type-link": {
                  "event-location-type-area": "CA085",
                  "link-road-designator": "I-280 S",
                  "link-from-road": "Magdalena Ave",
                  "link-to-road": null,
                  "link-from-city": "Los Altos",
                  "link-to-city": null,
                  "link-primary-location": {
                    "event-location-coordinates-latitude": "37.355142",
                    "event-location-coordinates-longitude": "-122.113546"
                  }
                }
              }
            },
            "event-element-times": {
              "update-time": "2022-05-10T16:48:43.23760",
              "valid-period": {
                "event-timeline-estimated-duration": "19"
              },
              "start-time": "2022-05-10T16:48:23.00000",
              "cleared-time": null,
              "utc-offset": "-0700"
            },
            "event-element-source": {
              "event-organization-reported-identifier": "1003"
            }
          }
        },
        "EventImpact": "Minor",
        "RoadClosed": "false",
        "ivr-eventStatus": "2",
        "ivr-eventClass": "1",
        "ivr-eventDirection": "Southbound",
        "ivr-lastUpdateDttm": "2022-05-10T16:48:43.23760",
        "ivr-article": "north of",
        "ivr-county": "Santa Clara",
        "ivr-laneStatus": "affected",
        "ivr-totalLanes": "Center Divider",
        "ivr-genOtherText": "Expect delays",
        "SourceEventID": "220510GG01626",
        "EventSourceName": "CHP",
        "ivr-completeFlag": "1"
      }
    },
    {
      "status": "ACTIVE",
      "headline": "CHP : Traffic Hazard on CA-37 Westbound east of Lakeville Hwy (Unincorporated). Lane blocked. Expect delays.",
      "event_type": "INCIDENT",
      "event_subtypes": {
        "event_subtype": "Traffic Hazard"
      },
      "severity": "Major",
      "created": "2022-05-10T23:48Z",
      "updated": "2022-05-10T23:48Z",
      "areas": {
        "area": {
          "name": "Sonoma",
          "id": "5397100",
          "link": {
            "@rel": "self",
            "@href": "http://geonames.org/5397100/"
          }
        }
      },
      "geography": {
        "crs": {
          "type": "name",
          "properties": {
            "name": "urn:ogc:def:crs:EPSG::4326"
          }
        },
        "type": "Point",
        "coordinates": [
          -122.492251,
          38.1244
        ]
      },
      "source_type": {
        "@xmlns": "http://511.org/open511-extensions",
        "#text": "CHP"
      },
      "source_id": {
        "@xmlns": "http://511.org/open511-extensions",
        "#text": "220510GG01623"
      },
      "roads": [
        {
          "name": "CA-37 W",
          "from": "Lakeville Hwy",
          "direction": "Westbound",
          "state": "SOME_LANES_CLOSED",
          "lane_type": {
            "@xmlns": "http://511.org/open511-extensions",
            "#text": "Lane"
          },
          "lane_status": {
            "@xmlns": "http://511.org/open511-extensions",
            "#text": "blocked"
          },
          "road_advisory": {
            "@xmlns": "http://511.org/open511-extensions",
            "#text": "Expect delays"
          },
          "article": {
            "@xmlns": "http://511.org/open511-extensions",
            "#text": "east of"
          }
        }
      ],
      "schedule": {
        "intervals": [
          "2022-05-10T23:48Z/"
        ]
      },
      "extension": {
        "message-header": {
          "event-message-time-stamp": "2022-05-10T16:49:07.13136"
        },
        "event-reference": {
          "event-identifier": "902387"
        },
        "event-status": "new",
        "details": {
          "eventElementDetails": {
            "event-element-sequence": "4",
            "event-element-description": {
              "eventDescription": [
                {
                  "event-phrase": {
                    "eventType": {
                      "incident": "Traffic Hazard"
                    }
                  }
                },
                {
                  "event-advice": "(unknown)"
                },
                {
                  "event-additional-text": {
                    "eventAdditionalText": {
                      "event-description": "CHP : Traffic Hazard on CA-37 Westbound east of Lakeville Hwy (Unincorporated). Lane blocked. Expect delays."
                    }
                  }
                }
              ]
            },
            "event-element-location": {
              "event-location-type": {
                "event-location-type-link": {
                  "event-location-type-area": "CA097",
                  "link-road-designator": "CA-37 W",
                  "link-from-road": "Lakeville Hwy",
                  "link-to-road": null,
                  "link-from-city": "Unincorporated",
                  "link-to-city": null,
                  "link-primary-location": {
                    "event-location-coordinates-latitude": "38.1244",
                    "event-location-coordinates-longitude": "-122.492251"
                  }
                }
              }
            },
            "event-element-times": {
              "update-time": "2022-05-10T16:48:23.52540",
              "valid-period": {
                "event-timeline-estimated-duration": "50.5"
              },
              "start-time": "2022-05-10T16:48:23.00000",
              "cleared-time": null,
              "utc-offset": "-0700"
            },
            "event-element-source": {
              "event-organization-reported-identifier": "1003"
            }
          }
        },
        "EventImpact": "Major",
        "RoadClosed": "false",
        "ivr-eventStatus": "2",
        "ivr-eventClass": "3",
        "ivr-eventDirection": "Westbound",
        "ivr-lastUpdateDttm": "2022-05-10T16:48:23.52540",
        "ivr-article": "east of",
        "ivr-county": "Sonoma",
        "ivr-laneStatus": "blocked",
        "ivr-totalLanes": "Lane",
        "ivr-genOtherText": "Expect delays",
        "SourceEventID": "220510GG01623",
        "EventSourceName": "CHP",
        "ivr-completeFlag": "1"
      }
    }
  ]
}
